cloudshell/__init__.py
cloudshell/cp/__init__.py
cloudshell/cp/core/__init__.py
cloudshell/cp/core/cancellation_manager.py
cloudshell/cp/core/exceptions.py
cloudshell/cp/core/reservation_info.py
cloudshell/cp/core/rollback.py
cloudshell/cp/core/flows/__init__.py
cloudshell/cp/core/flows/app_security_groups.py
cloudshell/cp/core/flows/cleanup_sandbox_infra.py
cloudshell/cp/core/flows/deploy.py
cloudshell/cp/core/flows/prepare_sandbox_infra.py
cloudshell/cp/core/flows/vm_details.py
cloudshell/cp/core/request_actions/__init__.py
cloudshell/cp/core/request_actions/base.py
cloudshell/cp/core/request_actions/cleanup_sandbox_infra.py
cloudshell/cp/core/request_actions/deploy_vm.py
cloudshell/cp/core/request_actions/deployed_vm.py
cloudshell/cp/core/request_actions/driver_response.py
cloudshell/cp/core/request_actions/get_vm_details.py
cloudshell/cp/core/request_actions/prepare_sandbox_infra.py
cloudshell/cp/core/request_actions/save_restore_app.py
cloudshell/cp/core/request_actions/set_app_security_groups.py
cloudshell/cp/core/request_actions/models/__init__.py
cloudshell/cp/core/request_actions/models/action_results.py
cloudshell/cp/core/request_actions/models/app_security_group.py
cloudshell/cp/core/request_actions/models/base.py
cloudshell/cp/core/request_actions/models/connectivity.py
cloudshell/cp/core/request_actions/models/create_keys.py
cloudshell/cp/core/request_actions/models/deploy_app.py
cloudshell/cp/core/request_actions/models/deployed_app.py
cloudshell/cp/core/request_actions/models/prepare_cloud_infra.py
cloudshell/cp/core/request_actions/models/prepare_subnet.py
cloudshell/cp/core/request_actions/models/save_restore_app.py
cloudshell/cp/core/request_actions/models/traffic_mirroring.py
cloudshell/cp/core/request_actions/models/validate_attributes.py
cloudshell/cp/core/utils/__init__.py
cloudshell/cp/core/utils/generate_ssh_key.py
cloudshell/cp/core/utils/name_generator.py
cloudshell/cp/core/utils/tags.py
tests/__init__.py
tests/cp/__init__.py
cloudshell_cp_core-2.5.4.dist-info/METADATA
cloudshell_cp_core-2.5.4.dist-info/WHEEL
cloudshell_cp_core-2.5.4.dist-info/top_level.txt
cloudshell_cp_core-2.5.4.dist-info/RECORD
