Metadata-Version: 2.1
Name: cloudshell-cp-core
Version: 2.5.4
Summary: A repository for projects providing out of the box capabilities within CloudShell to parse and convert cloudShell driver request to well defined python objects. One cloudshell-cp-core For All cloudshell cloud provider shells.
Home-page: http://www.qualisystems.com/
Author: Quali
Author-email: info@quali.com
Keywords: sandbox cloudshell json request
Requires-Python: ~=3.7
Requires-Dist: attrs (~=21.4)
Requires-Dist: jsonpickle (~=1.4.1)
Requires-Dist: cryptography (<3.3,>=2.9.2) ; python_version <= "3.7"
Requires-Dist: cached-property (~=1.5) ; python_version <= "3.8"
Requires-Dist: cryptography (<37,>=3.3) ; python_version > "3.7"
